[
	[
		{
			"num": 1,
			"price": 12000,
			"addition": [
				{
					"name" : "bieres",
					"value" : 5000,
					"sentence" : "+ 5000 tonnes de production de {value}"
				}
			]
		},
		{
			"num": 2,
			"price": 20000,
			"addition": [
				{
					"name" : "bieres",
					"value" : 15000,
					"sentence" : "+ 15000 tonnes de production de {value}"
				}
			]
		},
		{
			"num": 3,
			"price": 25000,
			"addition": [
				{
					"name" : "bieres",
					"value" : 25000,
					"sentence" : "+ 25000 tonnes de production de {value}"
				}
			]
		}
	]
]
